[
  {
    "src": "/client_logos/hbl_microfinancebank.png",
    "alt": "HBL Microfinance Logo"
  },
  { "src": "/client_logos/nikzn2.png", "alt": "Nikzn logo" },
  {
    "src": "/client_logos/apna_microfinancebank.png",
    "alt": "Apna Micro Finance bank logo"
  },
  {
    "src": "/client_logos/beyond_borders_education.png",
    "alt": "Beyond Borders Education logo"
  },
  {
    "src": "/client_logos/addiction2.png",
    "alt": "Addiction Clothing Brand Logo"
  },
  {
    "src": "/client_logos/LOLC_microfinancebank.png",
    "alt": "LOLC Micro Finance bank logo"
  }
]
